tflow/__init__.py
tflow/__main__.py
tflow/cli.py
tflow/cli_args.py
tflow/gitlab-ci.tmpl
tflow/render.py
tflow-0.0.8.dist-info/METADATA
tflow-0.0.8.dist-info/WHEEL
tflow-0.0.8.dist-info/entry_points.txt
tflow-0.0.8.dist-info/top_level.txt
tflow-0.0.8.dist-info/RECORD
